test_cli_fake/_init__.py
test_cli_fake/main.py
test_cli_fake-1.2.0.dist-info/METADATA
test_cli_fake-1.2.0.dist-info/WHEEL
test_cli_fake-1.2.0.dist-info/entry_points.txt
test_cli_fake-1.2.0.dist-info/RECORD
