Metadata-Version: 2.3
Name: test-cli-fake
Version: 1.2.0
Summary: Démo éducative d'une fausse commande CLI via entry point Python
License: MIT
Author: Cyriac Benousaad
Requires-Python: >=3.8,<4.0
Classifier: License :: OSI Approved :: MIT License
Classifier: Programming Language :: Python :: 3
Classifier: Programming Language :: Python :: 3.8
Classifier: Programming Language :: Python :: 3.9
Classifier: Programming Language :: Python :: 3.10
Classifier: Programming Language :: Python :: 3.11
Classifier: Programming Language :: Python :: 3.12
Classifier: Programming Language :: Python :: 3.13
